CHANGELOG.md
LICENSE
MANIFEST.in
Makefile
README.rst
setup.cfg
setup.py
umbr_api/__about__.py
umbr_api/__init__.py
umbr_api/_http_requests.py
umbr_api/add.py
umbr_api/credentials.py
umbr_api/get.py
umbr_api/management.py
umbr_api/remove.py
umbr_api/reporting.py
umbr_api/umbrella.py
umbr_api.egg-info/PKG-INFO
umbr_api.egg-info/SOURCES.txt
umbr_api.egg-info/dependency_links.txt
umbr_api.egg-info/entry_points.txt
umbr_api.egg-info/requires.txt
umbr_api.egg-info/top_level.txt
umbr_api.egg-info/zip-safe
umbr_api/data/umbrella.jpg
umbr_api/data/umbrella_example.json