Metadata-Version: 2.1
Name: umbr-api
Version: 1.0.3
Summary: Cisco Umbrella APIs wrapper and command-line utility
Home-page: https://github.com/kolatz/umbr_api
Author: kolatz
Author-email: private@example.com
License: MIT
Project-URL: Cisco Umbrella, https://umbrella.cisco.com/
Project-URL: Cisco Umbrella Enforcement API, https://docs.umbrella.com/developer/enforcement-api/
Keywords: cisco umbrella opendns security
Platform: Darwin
Classifier: Development Status :: 5 - Production/Stable
Classifier: Intended Audience :: Education
Classifier: Intended Audience :: System Administrators
Classifier: Topic :: Internet :: Name Service (DNS)
Classifier: Topic :: Security
Classifier: Topic :: Utilities
Classifier: Environment :: Console
Classifier: License :: OSI Approved :: MIT License
Classifier: Operating System :: MacOS
Classifier: Operating System :: Microsoft :: Windows
Classifier: Operating System :: POSIX :: Linux
Classifier: Programming Language :: Python
Classifier: Programming Language :: Python :: 3.5
Classifier: Programming Language :: Python :: 3.6
Classifier: Programming Language :: Python :: 3.7
Classifier: Programming Language :: Python :: 3 :: Only
Classifier: Programming Language :: Python :: Implementation :: CPython
Provides-Extra: dev
Provides-Extra: lint_opt
Provides-Extra: lint_dev
Provides-Extra: doc
